verma/__init__.py
verma-0.1.1.dist-info/LICENSE
verma-0.1.1.dist-info/METADATA
verma-0.1.1.dist-info/WHEEL
verma-0.1.1.dist-info/entry_points.txt
verma-0.1.1.dist-info/top_level.txt
verma-0.1.1.dist-info/RECORD
