Metadata-Version: 2.1
Name: verma
Version: 0.1.1
Summary: Version Manager. CLI tool to help you manage your package versioning.
Author: Carlos Colin
Requires-Python: >=3.11
License-File: LICENSE
Requires-Dist: click ==8.1.7
Requires-Dist: gitpython ==3.1.35
